CHANGES
MANIFEST.in
README.rst
setup.cfg
setup.py
statsd_cloudwatch/__init__.py
statsd_cloudwatch/main.py
statsd_cloudwatch.egg-info/PKG-INFO
statsd_cloudwatch.egg-info/SOURCES.txt
statsd_cloudwatch.egg-info/dependency_links.txt
statsd_cloudwatch.egg-info/entry_points.txt
statsd_cloudwatch.egg-info/not-zip-safe
statsd_cloudwatch.egg-info/requires.txt
statsd_cloudwatch.egg-info/top_level.txt